aiopyrq/__init__.py
aiopyrq/helpers.py
aiopyrq/pools.py
aiopyrq/queues.py
aiopyrq/unique_queues.py
aio_py_rq-4.1.0.dist-info/LICENSE
aio_py_rq-4.1.0.dist-info/METADATA
aio_py_rq-4.1.0.dist-info/WHEEL
aio_py_rq-4.1.0.dist-info/RECORD
