Metadata-Version: 2.1
Name: aio-py-rq
Version: 4.1.0
Summary: 
Author: Heureka
Author-email: vyvoj@heureka.cz
Requires-Python: >=3.7,<4.0
Classifier: Programming Language :: Python :: 3
Classifier: Programming Language :: Python :: 3.7
Classifier: Programming Language :: Python :: 3.8
Classifier: Programming Language :: Python :: 3.9
Classifier: Programming Language :: Python :: 3.10
Classifier: Programming Language :: Python :: 3.11
Requires-Dist: redis (>=5.0.0,<6.0.0)
